paradigm/__init__.py
paradigm/base.py
paradigm/py.typed
paradigm/_core/__init__.py
paradigm/_core/annotated.py
paradigm/_core/caching.py
paradigm/_core/catalog.py
paradigm/_core/discovery.py
paradigm/_core/file_system.py
paradigm/_core/index.py
paradigm/_core/models.py
paradigm/_core/modules.py
paradigm/_core/namespacing.py
paradigm/_core/pretty.py
paradigm/_core/scoping.py
paradigm/_core/signatures.py
paradigm/_core/sources.py
paradigm/_core/stubs.py
paradigm/_core/utils.py
paradigm/_core/arboreal/__init__.py
paradigm/_core/arboreal/construction.py
paradigm/_core/arboreal/conversion.py
paradigm/_core/arboreal/evaluation.py
paradigm/_core/arboreal/execution.py
paradigm/_core/arboreal/kind.py
paradigm/_core/arboreal/utils.py
paradigm-4.4.1.dist-info/licenses/LICENSE
paradigm-4.4.1.dist-info/METADATA
paradigm-4.4.1.dist-info/WHEEL
paradigm-4.4.1.dist-info/top_level.txt
paradigm-4.4.1.dist-info/RECORD
