Metadata-Version: 2.4
Name: paradigm
Version: 4.4.1
Summary: Python objects metadata parser.
Home-page: https://github.com/lycantropos/paradigm/
Download-URL: https://github.com/lycantropos/paradigm/archive/master.zip
Author-email: Azat Ibrakov <azatibrakov@gmail.com>
License: MIT License
Classifier: License :: OSI Approved :: MIT License
Classifier: Programming Language :: Python :: 3.10
Classifier: Programming Language :: Python :: 3.11
Classifier: Programming Language :: Python :: 3.12
Classifier: Programming Language :: Python :: 3.13
Classifier: Programming Language :: Python :: Implementation :: CPython
Requires-Python: >=3.10
License-File: LICENSE
Requires-Dist: mypy<2.0,>=1.17.0
Requires-Dist: typing-extensions<5.0,>=4.14.1
Provides-Extra: tests
Requires-Dist: hypothesis<7.0,>=6.135.14; extra == "tests"
Requires-Dist: pytest>=8.4.1; extra == "tests"
Dynamic: download-url
Dynamic: home-page
Dynamic: license-file
